dictaclass/__init__.py
dictaclass/dictaclass.py
dictaclass-0.6.0.dist-info/METADATA
dictaclass-0.6.0.dist-info/WHEEL
dictaclass-0.6.0.dist-info/licenses/LICENSE.txt
dictaclass-0.6.0.dist-info/RECORD
