Metadata-Version: 2.3
Name: dictaclass
Version: 0.6.0
Summary: Convert heirarchies of dicts/list/sets/values (JSON?) to heirarchies of type annotated dataclasses.
Project-URL: Homepage, https://github.com/BraynStorm/dictaclass
Project-URL: Bug Tracker, https://github.com/BraynStorm/dictaclass/issues
Author-email: Bozhidar Stoyanov <glav0r3zzz4@gmail.com>
License-File: LICENSE.txt
Classifier: License :: OSI Approved :: Apache Software License
Classifier: Operating System :: OS Independent
Classifier: Programming Language :: Python :: 3
Requires-Python: >=3.7.2
